botprogramminginterface.py
botprogramminginterface-0.0.1.dist-info/WHEEL
botprogramminginterface-0.0.1.dist-info/METADATA
botprogramminginterface-0.0.1.dist-info/RECORD
